pyregularexpression/__init__.py
pyregularexpression/adherence_compliance_finder.py
pyregularexpression/algorithm_validation_finder.py
pyregularexpression/allocation_concealment_finder.py
pyregularexpression/apply_regex_functions.py
pyregularexpression/attrition_criteria_finder.py
pyregularexpression/background_rationale_finder.py
pyregularexpression/baseline_data_finder.py
pyregularexpression/blinding_masking_finder.py
pyregularexpression/changes_to_outcomes_finder.py
pyregularexpression/comparator_cohort_finder.py
pyregularexpression/competing_risk_analysis_finder.py
pyregularexpression/conflict_of_interest_finder.py
pyregularexpression/covariate_adjustment_finder.py
pyregularexpression/data_access_finder.py
pyregularexpression/data_linkage_method_finder.py
pyregularexpression/data_provenance_finder.py
pyregularexpression/data_safety_monitoring_finder.py
pyregularexpression/data_sharing_statement_finder.py
pyregularexpression/data_source_type_finder.py
pyregularexpression/demographic_restriction_finder.py
pyregularexpression/dose_response_analysis_finder.py
pyregularexpression/eligibility_criteria_finder.py
pyregularexpression/entry_event_finder.py
pyregularexpression/ethics_approval_finder.py
pyregularexpression/event_adjudication_finder.py
pyregularexpression/exclusion_rule_finder.py
pyregularexpression/exit_criterion_finder.py
pyregularexpression/exposure_definition_finder.py
pyregularexpression/extract_regex_paragraphs_udf.py
pyregularexpression/follow_up_period_finder.py
pyregularexpression/funding_statement_finder.py
pyregularexpression/generalizability_finder.py
pyregularexpression/harms_adverse_event_finder.py
pyregularexpression/healthcare_setting_finder.py
pyregularexpression/inclusion_rule_finder.py
pyregularexpression/index_date_finder.py
pyregularexpression/interim_analysis_stopping_rules_finder.py
pyregularexpression/interventions_finder.py
pyregularexpression/limitations_finder.py
pyregularexpression/losses_exclusion_finder.py
pyregularexpression-0.1.0.dist-info/licenses/LICENSE
pyregularexpression-0.1.0.dist-info/METADATA
pyregularexpression-0.1.0.dist-info/WHEEL
pyregularexpression-0.1.0.dist-info/top_level.txt
pyregularexpression-0.1.0.dist-info/RECORD
