Metadata-Version: 2.4
Name: pyregularexpression
Version: 0.1.0
Summary: Collection of reusable regular‑expression patterns
Author-email: Gowtham Rao <rao@ohdsi.org>
License:                                  Apache License
Project-URL: Homepage, https://github.com/OHDSI/pyRegularExpression
Project-URL: BugTracker, https://github.com/OHDSI/pyRegularExpression/issues
Keywords: regex,regular expressions,patterns
Classifier: Programming Language :: Python :: 3
Classifier: License :: OSI Approved :: Apache Software License
Classifier: Operating System :: OS Independent
Classifier: Topic :: Text Processing :: General
Requires-Python: >=3.10
License-File: LICENSE
Requires-Dist: pandas
Requires-Dist: numpy
Provides-Extra: spark
Requires-Dist: pyspark; extra == "spark"
Requires-Dist: pyarrow; extra == "spark"
Provides-Extra: dev
Requires-Dist: pytest>=7.0; extra == "dev"
Requires-Dist: pytest-cov; extra == "dev"
Requires-Dist: black>=24.0; extra == "dev"
Requires-Dist: mypy>=1.8; extra == "dev"
Requires-Dist: ruff>=0.4.0; extra == "dev"
Requires-Dist: nltk; extra == "dev"
Dynamic: license-file
